Workbook
Name aporte: Planilha1!$E$19
Name patrimonio_acumulado: Planilha1!$E$22
Name qtde_anos: Planilha1!$E$20
Name rendimento_carteira: Planilha1!$E$15
Name salario: Planilha1!$E$14
Name sugestao_investimento: Planilha1!$E$16
Name taxa_mensal: Planilha1!$E$21

Sheet Planilha1
C10: INVESTIMENTOS IMOBILIÁRIOS
C11: SIMULAÇÃO DE VALORES
C13: CONFIGURAÇÕES
C14: Salário | E14: 5000
C15: Rendimento de Carteira | E15: 0.01079
C16: Sugestão de Investimento | E16: =E14*30% -> 1500
C18: INVESTIMENTO MENSAL
C19: Quanto investir por mês? | E19: 200
C20: Por quantos anos? | E20: 5
C21: Taxa de Rendimento Mensal? | E21: 0.01079
C22: Patrimônio Acumulado | E22: =FV(taxa_mensal,12*qtde_anos,aporte*-1) -> 16755.383
C23: Dividendos mensais | E23: =patrimonio_acumulado*taxa_mensal -> 180.79058
C25: CENÁRIOS | E25: DIVIDENDOS
C26: Quanto em 02 anos? | D26: =FV($E$21,2*12,$E$19*-1) -> 5445.5255 | E26: =D26*rendimento_carteira -> 58.75722
C27: Quanto em 05 anos? | D27: =FV($E$21,5*12,$E$19*-1) -> 16755.383 | E27: =D27*rendimento_carteira -> 180.79058
C28: Quanto em 10 anos? | D28: =FV($E$21,10*12,$E$19*-1) -> 48656.843 | E28: =D28*rendimento_carteira -> 525.00733
C29: Quanto em 20 anos? | D29: =FV($E$21,20*12,$E$19*-1) -> 225039.68 | E29: =D29*rendimento_carteira -> 2428.1781
C30: Quanto em 30 anos? | D30: =FV($E$21,30*12,$E$19*-1) -> 864433.93 | E30: =D30*rendimento_carteira -> 9327.2421
C32: PERFIL INVESTIDOR | D32: Conservador
C33: VALOR A SER INVESTIDO POR MÊS | D33: =aporte -> 200
C35: TIPO DE FII | D35: Percentual Sugerido | E35: Valores
C36: PAPEL | D36: =VLOOKUP($D$32&"-"&C36,Planilha2!$B$5:$E$22,4,) -> 0.5 | E36: =$D$33*D36 -> 100
C37: TIJOLO | D37: =VLOOKUP($D$32&"-"&C37,Planilha2!$B$5:$E$22,4,) -> 0.3 | E37: =$D$33*D37 -> 60
C38: HÍBRIDO | D38: =VLOOKUP($D$32&"-"&C38,Planilha2!$B$5:$E$22,4,) -> 0.1 | E38: =$D$33*D38 -> 20
C39: FOFs | D39: =VLOOKUP($D$32&"-"&C39,Planilha2!$B$5:$E$22,4,) -> 0.1 | E39: =$D$33*D39 -> 20
C40: DESENVOLVIMENTO | D40: =VLOOKUP($D$32&"-"&C40,Planilha2!$B$5:$E$22,4,) -> 0 | E40: =$D$33*D40 -> 0
C41: HOTELARIA | D41: =VLOOKUP($D$32&"-"&C41,Planilha2!$B$5:$E$22,4,) -> 0 | E41: =$D$33*D41 -> 0
C42: TOTAL | E42: =SUM(E36:E41) -> 200

Sheet Planilha2
B2: TABELA DE DADOS AUXILIAR
B4: CHAVE | C4: PERFIL | D4: TIPO DE FII | E4: Percentual Sugerido
B5: =C5&"-"&D5 -> Conservador-PAPEL | C5: Conservador | D5: PAPEL | E5: 0.5
B6: =C6&"-"&D6 -> Conservador-TIJOLO | C6: Conservador | D6: TIJOLO | E6: 0.3
B7: =C7&"-"&D7 -> Conservador-HÍBRIDO | C7: Conservador | D7: HÍBRIDO | E7: 0.1
B8: =C8&"-"&D8 -> Conservador-FOFs | C8: Conservador | D8: FOFs | E8: 0.1
B9: =C9&"-"&D9 -> Conservador-DESENVOLVIMENTO | C9: Conservador | D9: DESENVOLVIMENTO | E9: 0
B10: =C10&"-"&D10 -> Conservador-HOTELARIA | C10: Conservador | D10: HOTELARIA | E10: 0
B11: =C11&"-"&D11 -> Moderado-PAPEL | C11: Moderado | D11: PAPEL | E11: 0.32
B12: =C12&"-"&D12 -> Moderado-TIJOLO | C12: Moderado | D12: TIJOLO | E12: 0.35
B13: =C13&"-"&D13 -> Moderado-HÍBRIDO | C13: Moderado | D13: HÍBRIDO | E13: 0.08
B14: =C14&"-"&D14 -> Moderado-FOFs | C14: Moderado | D14: FOFs | E14: 0.05
B15: =C15&"-"&D15 -> Moderado-DESENVOLVIMENTO | C15: Moderado | D15: DESENVOLVIMENTO | E15: 0.1
B16: =C16&"-"&D16 -> Moderado-HOTELARIA | C16: Moderado | D16: HOTELARIA | E16: 0.1
... B22: =C22&"-"&D22 -> Agressivo-HOTELARIA | C22: Agressivo | D22: HOTELARIA | E22: 0.1
